{
    "key": "group_62da7fa00e1fd",
    "title": "Admin Settings",
    "fields": [
        {
            "key": "field_62da7fa700915",
            "label": "Site Logo and Favicon Settings",
            "name": "",
            "aria-label": "",
            "type": "tab",
            "instructions": "",
            "required": 0,
            "conditional_logic": 0,
            "wrapper": {
                "width": "",
                "class": "",
                "id": ""
            },
            "placement": "top",
            "endpoint": 0
        },
        {
            "key": "field_62da7fea00916",
            "label": "Logo",
            "name": "logo",
            "aria-label": "",
            "type": "image",
            "instructions": "",
            "required": 0,
            "conditional_logic": 0,
            "wrapper": {
                "width": "",
                "class": "",
                "id": ""
            },
            "return_format": "url",
            "preview_size": "medium",
            "library": "all",
            "min_width": "",
            "min_height": "",
            "min_size": "",
            "max_width": "",
            "max_height": "",
            "max_size": "",
            "mime_types": ""
        },
        {
            "key": "field_62da800200917",
            "label": "Site Styling",
            "name": "",
            "aria-label": "",
            "type": "tab",
            "instructions": "",
            "required": 0,
            "conditional_logic": 0,
            "wrapper": {
                "width": "",
                "class": "",
                "id": ""
            },
            "placement": "top",
            "endpoint": 0
        },
        {
            "key": "field_62ed01c37e22d",
            "label": "Primary Color",
            "name": "global_theme_color1",
            "aria-label": "",
            "type": "color_picker",
            "instructions": "",
            "required": 0,
            "conditional_logic": 0,
            "wrapper": {
                "width": "",
                "class": "",
                "id": ""
            },
            "default_value": "",
            "enable_opacity": 0,
            "return_format": "string"
        },
        {
            "key": "field_62ed01e07e22e",
            "label": "Secondary Color",
            "name": "global_theme_color2",
            "aria-label": "",
            "type": "color_picker",
            "instructions": "",
            "required": 0,
            "conditional_logic": 0,
            "wrapper": {
                "width": "",
                "class": "",
                "id": ""
            },
            "default_value": "",
            "enable_opacity": 0,
            "return_format": "string"
        },
        {
            "key": "field_62ed01e97e22f",
            "label": "Global Theme Color3",
            "name": "global_theme_color3",
            "aria-label": "",
            "type": "color_picker",
            "instructions": "",
            "required": 0,
            "conditional_logic": 0,
            "wrapper": {
                "width": "",
                "class": "",
                "id": ""
            },
            "default_value": "",
            "enable_opacity": 0,
            "return_format": "string"
        },
        {
            "key": "field_62ed01ff7e230",
            "label": "Global Theme Color4",
            "name": "global_theme_color4",
            "aria-label": "",
            "type": "color_picker",
            "instructions": "",
            "required": 0,
            "conditional_logic": 0,
            "wrapper": {
                "width": "",
                "class": "",
                "id": ""
            },
            "default_value": "",
            "enable_opacity": 0,
            "return_format": "string"
        },
        {
            "key": "field_62ed020f7e231",
            "label": "Global Theme Color5",
            "name": "global_theme_color5",
            "aria-label": "",
            "type": "color_picker",
            "instructions": "",
            "required": 0,
            "conditional_logic": 0,
            "wrapper": {
                "width": "",
                "class": "",
                "id": ""
            },
            "default_value": "",
            "enable_opacity": 0,
            "return_format": "string"
        },
        {
            "key": "field_62ed02177e232",
            "label": "Global Theme Color6",
            "name": "global_theme_color6",
            "aria-label": "",
            "type": "color_picker",
            "instructions": "",
            "required": 0,
            "conditional_logic": 0,
            "wrapper": {
                "width": "",
                "class": "",
                "id": ""
            },
            "default_value": "",
            "enable_opacity": 0,
            "return_format": "string"
        },
        {
            "key": "field_62ed0823ea9ad",
            "label": "Global Theme Color7",
            "name": "global_theme_color7",
            "aria-label": "",
            "type": "color_picker",
            "instructions": "",
            "required": 0,
            "conditional_logic": 0,
            "wrapper": {
                "width": "",
                "class": "",
                "id": ""
            },
            "default_value": "",
            "enable_opacity": 0,
            "return_format": "string"
        },
        {
            "key": "field_647fd7b7d85c1",
            "label": "Copyright Color",
            "name": "copyright_color",
            "aria-label": "",
            "type": "color_picker",
            "instructions": "",
            "required": 0,
            "conditional_logic": 0,
            "wrapper": {
                "width": "",
                "class": "",
                "id": ""
            },
            "default_value": "#fefefe",
            "enable_opacity": 0,
            "return_format": "string"
        },
        {
            "key": "field_62da85b882311",
            "label": "Custom Embed Code - Head",
            "name": "custom_embed_code_head",
            "aria-label": "",
            "type": "textarea",
            "instructions": "Enter any custom embed codes here. They will be output in the element.",
            "required": 0,
            "conditional_logic": 0,
            "wrapper": {
                "width": "",
                "class": "",
                "id": ""
            },
            "default_value": "",
            "placeholder": "",
            "maxlength": "",
            "rows": "",
            "new_lines": ""
        },
        {
            "key": "field_62da85c982312",
            "label": "Custom Embed Code - After Body",
            "name": "custom_embed_code_after_body",
            "aria-label": "",
            "type": "textarea",
            "instructions": "Enter any custom embed codes here. They will be output right after the element.",
            "required": 0,
            "conditional_logic": 0,
            "wrapper": {
                "width": "",
                "class": "",
                "id": ""
            },
            "default_value": "",
            "placeholder": "",
            "maxlength": "",
            "rows": "",
            "new_lines": ""
        },
        {
            "key": "field_62da85d882313",
            "label": "Custom Embed Code - Footer",
            "name": "custom_embed_code_-_footer",
            "aria-label": "",
            "type": "textarea",
            "instructions": "Enter any custom embed codes here. They will be output before the closing tag",
            "required": 0,
            "conditional_logic": 0,
            "wrapper": {
                "width": "",
                "class": "",
                "id": ""
            },
            "default_value": "",
            "placeholder": "",
            "maxlength": "",
            "rows": "",
            "new_lines": ""
        },
        {
            "key": "field_642d6e4a63963",
            "label": "Custom CSS",
            "name": "header_custom_css",
            "aria-label": "",
            "type": "textarea",
            "instructions": "",
            "required": 0,
            "conditional_logic": 0,
            "wrapper": {
                "width": "",
                "class": "",
                "id": ""
            },
            "default_value": "",
            "maxlength": "",
            "rows": "",
            "placeholder": "",
            "new_lines": ""
        },        
        {
            "key": "field_655f50c535485",
            "label": "Enable Features",
            "name": "",
            "aria-label": "",
            "type": "tab",
            "instructions": "",
            "required": 0,
            "conditional_logic": 0,
            "wrapper": {
                "width": "",
                "class": "",
                "id": ""
            },
            "placement": "top",
            "endpoint": 0
        },
        {
            "key": "field_655f50e132481",
            "label": "Posts",
            "name": "enable_posts",
            "aria-label": "",
            "type": "true_false",
            "instructions": "",
            "required": 0,
            "conditional_logic": 0,
            "wrapper": {
                "width": "25",
                "class": "",
                "id": ""
            },
            "message": "",
            "default_value": 1,
            "ui_on_text": "On",
            "ui_off_text": "Off",
            "ui": 1
        },
        {
            "key": "field_655f50e135486",
            "label": "Weekly Digests",
            "name": "enable_weeklydigests",
            "aria-label": "",
            "type": "true_false",
            "instructions": "",
            "required": 0,
            "conditional_logic": 0,
            "wrapper": {
                "width": "25",
                "class": "",
                "id": ""
            },
            "message": "",
            "default_value": 1,
            "ui_on_text": "On",
            "ui_off_text": "Off",
            "ui": 1
        },
        {
            "key": "field_655f510c35487",
            "label": "Packages",
            "name": "enable_packages",
            "aria-label": "",
            "type": "true_false",
            "instructions": "",
            "required": 0,
            "conditional_logic": 0,
            "wrapper": {
                "width": "25",
                "class": "",
                "id": ""
            },
            "message": "",
            "default_value": 1,
            "ui_on_text": "On",
            "ui_off_text": "Off",
            "ui": 1
        },
        {
            "key": "field_655f513035488",
            "label": "Testimonials",
            "name": "enable_testimonials",
            "aria-label": "",
            "type": "true_false",
            "instructions": "",
            "required": 0,
            "conditional_logic": 0,
            "wrapper": {
                "width": "25",
                "class": "",
                "id": ""
            },
            "message": "",
            "default_value": 1,
            "ui_on_text": "On",
            "ui_off_text": "Off",
            "ui": 1
        },
        {
            "key": "field_655f516035488",
            "label": "Team Members",
            "name": "enable_teammembers",
            "aria-label": "",
            "type": "true_false",
            "instructions": "",
            "required": 0,
            "conditional_logic": 0,
            "wrapper": {
                "width": "25",
                "class": "",
                "id": ""
            },
            "message": "",
            "default_value": 1,
            "ui_on_text": "On",
            "ui_off_text": "Off",
            "ui": 1
        },
        {
            "key": "field_655f516c35489",
            "label": "Resources",
            "name": "enable_resources",
            "aria-label": "",
            "type": "true_false",
            "instructions": "",
            "required": 0,
            "conditional_logic": 0,
            "wrapper": {
                "width": "25",
                "class": "",
                "id": ""
            },
            "message": "",
            "default_value": 1,
            "ui_on_text": "On",
            "ui_off_text": "Off",
            "ui": 1
        },
        {
            "key": "field_655f51763548a",
            "label": "Landing Pages",
            "name": "enable_landingpages",
            "aria-label": "",
            "type": "true_false",
            "instructions": "",
            "required": 0,
            "conditional_logic": 0,
            "wrapper": {
                "width": "25",
                "class": "",
                "id": ""
            },
            "message": "",
            "default_value": 1,
            "ui_on_text": "On",
            "ui_off_text": "Off",
            "ui": 1
        },
        {
            "key": "field_655f518c3548b",
            "label": "Mail Posts & Mail Templates",
            "name": "enable_mail_posts_mail_templates",
            "aria-label": "",
            "type": "true_false",
            "instructions": "",
            "required": 0,
            "conditional_logic": 0,
            "wrapper": {
                "width": "25",
                "class": "",
                "id": ""
            },
            "message": "",
            "default_value": 1,
            "ui_on_text": "On",
            "ui_off_text": "Off",
            "ui": 1
        },
        {
            "key": "field_655f51a33548c",
            "label": "Checklists",
            "name": "enable_checklists",
            "aria-label": "",
            "type": "true_false",
            "instructions": "",
            "required": 0,
            "conditional_logic": 0,
            "wrapper": {
                "width": "25",
                "class": "",
                "id": ""
            },
            "message": "",
            "default_value": 1,
            "ui_on_text": "On",
            "ui_off_text": "Off",
            "ui": 1
        },
        {
            "key": "field_655f51ae3548d",
            "label": "Videos",
            "name": "enable_videos",
            "aria-label": "",
            "type": "true_false",
            "instructions": "",
            "required": 0,
            "conditional_logic": 0,
            "wrapper": {
                "width": "25",
                "class": "",
                "id": ""
            },
            "message": "",
            "default_value": 1,
            "ui_on_text": "On",
            "ui_off_text": "Off",
            "ui": 1
        }
    ],
    "location": [
        [
            {
                "param": "options_page",
                "operator": "==",
                "value": "acf-options-admin-settings"
            }
        ]
    ],
    "menu_order": 0,
    "position": "normal",
    "style": "default",
    "label_placement": "top",
    "instruction_placement": "label",
    "hide_on_screen": "",
    "active": true,
    "description": "",
    "show_in_rest": 0,
    "modified": 1700460652
}
